{
    "needsErrorInfo": false,
    "mobileBottomRow": 23,
    "widgetName": "Text3",
    "iconSVG": "https://cdn.zuora.com/extension-studio/static/media/icon.a55b701a2ae86aa2c6718ecb7b4083f0.svg",
    "displayName": "Text",
    "topRow": 19,
    "searchTags": [
        "typography",
        "paragraph",
        "label"
    ],
    "bottomRow": 23,
    "parentRowSpace": 10,
    "type": "TEXT_WIDGET",
    "hideCard": false,
    "mobileRightColumn": 22,
    "animateLoading": true,
    "overflow": "NONE",
    "fontFamily": "{{appsmith.theme.fontFamily.appFont}}",
    "parentColumnSpace": 11.890625,
    "dynamicTriggerPathList": [],
    "leftColumn": 6,
    "dynamicBindingPathList": [
        {"key": "truncateButtonColor"},
        {"key": "fontFamily"},
        {"key": "borderRadius"}
    ],
    "shouldTruncate": false,
    "truncateButtonColor": "{{appsmith.theme.colors.primaryColor}}",
    "text": "test label",
    "key": "6oou5taxzg",
    "isDeprecated": false,
    "rightColumn": 22,
    "thumbnailSVG": "https://cdn.zuora.com/extension-studio/static/media/thumbnail.0c129b82c9b3e4cd4920563b289659ab.svg",
    "textAlign": "LEFT",
    "dynamicHeight": "AUTO_HEIGHT",
    "widgetId": "141ialroij",
    "onCanvasUI": {
        "focusBGCSSVar": "--on-canvas-ui-widget-focus",
        "disableParentSelection": false,
        "focusColorCSSVar": "--on-canvas-ui-widget-selection",
        "selectionBGCSSVar": "--on-canvas-ui-widget-selection",
        "selectionColorCSSVar": "--on-canvas-ui-widget-focus"
    },
    "minWidth": 450,
    "isVisible": true,
    "fontStyle": "BOLD",
    "textColor": "#231F20",
    "version": 1,
    "parentId": "0",
    "tags": [
        "Suggested",
        "Content"
    ],
    "isLoading": false,
    "renderMode": "CANVAS",
    "mobileTopRow": 19,
    "responsiveBehavior": "fill",
    "originalTopRow": 19,
    "borderRadius": "{{appsmith.theme.borderRadius.appBorderRadius}}",
    "mobileLeftColumn": 6,
    "maxDynamicHeight": 9000,
    "originalBottomRow": 23,
    "fontSize": "1rem",
    "minDynamicHeight": 4
}